openvpnzone
version
config
