Metadata-Version: 1.1
Name: openvpn2dns
Version: 1.1.0
Summary: DNS server in python serving openvpn status files as dns zones
Home-page: https://github.com/mswart/openvpn2dns
Author: Malte Swart
Author-email: mswart@devtation.de
License: MIT
Keywords: openvpn twisted dns
Platform: UNKNOWN
Classifier: Development Status :: 5 - Production/Stable
Classifier: Intended Audience :: System Administrators
Classifier: Topic :: Internet :: Name Service (DNS)
Classifier: Topic :: System :: Networking
Classifier: Topic :: Communications
Classifier: License :: OSI Approved :: MIT License
Classifier: Programming Language :: Python :: 2 :: Only
Classifier: Programming Language :: Python :: 2.6
Classifier: Programming Language :: Python :: 2.7
